COPYRIGHT
MANIFEST.in
README.pnw
README.rst
__version__.py
makefile
pnw-doc.pdf
pnw.pnw
setup.py
doc/latex-blocks.tex
doc/latex-blocks.tex~
doc/makefile
doc/makefile~
doc/md-blocks
doc/md-blocks~
doc/pnw-doc.pdf
doc/pnw-doc.pnw
doc/pnw-doc.pnw~
doc/pnw-doc.tex
doc/sicherung.pnw
doc/build/__version__
doc/build/amsalpha-lmp.bst
doc/build/hginfo.blg
doc/build/local.sty
doc/build/localbib.bib
doc/build/localbib.bib~
doc/build/makefile
doc/build/makefile~
doc/build/ml-gen.cls
doc/build/ml-gen.cls~
doc/build/pnw-doc.aux
doc/build/pnw-doc.bbl
doc/build/pnw-doc.blg
doc/build/pnw-doc.brf
doc/build/pnw-doc.log
doc/build/pnw-doc.out
doc/build/pnw-doc.pdf
doc/build/pnw-doc.tex
doc/build/pnw-doc.tex~
doc/build/pnw-doc.toc
doc/build/pnw.log
pnw/__init__.py
pnw/__version__.py
pnw/pnw.py
pnw.egg-info/PKG-INFO
pnw.egg-info/SOURCES.txt
pnw.egg-info/dependency_links.txt
pnw.egg-info/top_level.txt
scripts/pnw