Metadata-Version: 1.0
Name: pnw
Version: 0.0.5r1
Summary: A text processing and literate programming tool inspired by antiweb, noweb
Home-page: UNKNOWN
Author: Matthias Lesch
Author-email: ml@matthiaslesch.de
License: Apache 2.0
Platform: UNKNOWN
